setup.py
kegmeter/__init__.py
kegmeter/app/Interface.py
kegmeter/app/Serial.py
kegmeter/app/Status.py
kegmeter/app/__init__.py
kegmeter/app/images/pbu_40_grey.png
kegmeter/app/interface/interface.css
kegmeter/app/interface/interface.glade
kegmeter_app.egg-info/PKG-INFO
kegmeter_app.egg-info/SOURCES.txt
kegmeter_app.egg-info/dependency_links.txt
kegmeter_app.egg-info/namespace_packages.txt
kegmeter_app.egg-info/requires.txt
kegmeter_app.egg-info/top_level.txt
scripts/kegmeter_app.py